<?xml version="1.0" encoding="UTF-8"?> <r xmlns:xsi="http://www.w3.org/2001/XMLSchema-instance" xmlns:xs="http://www.w3.org/2001/XMLSchema" xmlns:hfp="http://www.w3.org/2001/XMLSchema-hasFacetAndProperty" xmlns:fn="http://www.w3.org/2005/02/xpath-functions" xsi:noNamespaceSchemaLocation="../../../../../gtcore/schemas/fiu-dict-schema.xsd" xml:lang="smn">
<e id="Clt_1">
   <lg>
     <l pos="Clt">râk</l>
   </lg>
   <mg rest="">
     <tg xml:lang="fin">
       <t pos="Clt">-pa ~ -pä</t>
     </tg>
   </mg>
</e>
</r> 
